dockbox/__init__.py
dockbox/autodock.py
dockbox/colvar.py
dockbox/dock.py
dockbox/dsx.py
dockbox/glide.py
dockbox/gold.py
dockbox/license.py
dockbox/method.py
dockbox/moe.py
dockbox/rundbx.py
dockbox/setconf.py
dockbox/vina.py
dockbox-1.2.data/scripts/extract_dbx_best_poses
dockbox-1.2.data/scripts/rundbx
dockbox-1.2.dist-info/LICENSE.txt
dockbox-1.2.dist-info/METADATA
dockbox-1.2.dist-info/WHEEL
dockbox-1.2.dist-info/top_level.txt
dockbox-1.2.dist-info/RECORD
