Metadata-Version: 2.1
Name: dockbox
Version: 1.2
Summary: Platform package to simplify the use of docking programs and consensus methods
Home-page: UNKNOWN
Author: UNKNOWN
Author-email: UNKNOWN
License: LICENSE.txt
Platform: UNKNOWN
Requires-Dist: mdkit
Requires-Dist: cython
Requires-Dist: numpy (==1.8.0)
Requires-Dist: pandas (==0.19.0)
